{"cameraMode":{"drawMode":0,"name":"Shaded","section":"Shading Mode"},"sceneLighting":true,"audioPlay":false,"sceneViewState":{"m_AlwaysRefresh":false,"showFog":true,"showSkybox":true,"showFlares":true,"showImageEffects":true,"showParticleSystems":true,"showVisualEffectGraphs":true,"m_FxEnabled":true},"in2DMode":false,"pivot":{"x":-7.100908279418945,"y":6.46560001373291,"z":10.901878356933594},"rotation":{"x":-0.04067249223589897,"y":0.7366552352905273,"z":-0.044481344521045688,"w":-0.673577070236206},"size":10.0,"orthographic":false}